odoo10_addon_connector_algolia-10.0.2.0.0.99.dev9-py3.8-nspkg.pth
odoo/addons/connector_algolia/README.rst
odoo/addons/connector_algolia/__init__.py
odoo/addons/connector_algolia/__manifest__.py
odoo/addons/connector_algolia/components/__init__.py
odoo/addons/connector_algolia/components/adapter.py
odoo/addons/connector_algolia/components/core.py
odoo/addons/connector_algolia/demo/backend_demo.xml
odoo/addons/connector_algolia/i18n/connector_algolia.pot
odoo/addons/connector_algolia/models/__init__.py
odoo/addons/connector_algolia/models/se_backend_algolia.py
odoo/addons/connector_algolia/readme/CHANGES.rst
odoo/addons/connector_algolia/readme/CONFIGURE.rst
odoo/addons/connector_algolia/readme/CONTRIBUTORS.rst
odoo/addons/connector_algolia/readme/DESCRIPTION.rst
odoo/addons/connector_algolia/readme/HISTORY.rst
odoo/addons/connector_algolia/security/ir.model.access.csv
odoo/addons/connector_algolia/static/description/icon.png
odoo/addons/connector_algolia/static/description/index.html
odoo/addons/connector_algolia/tests/__init__.py
odoo/addons/connector_algolia/tests/test_se_algolia.py
odoo/addons/connector_algolia/tests/cassettes/TestAlgoliaBackend.test_delete_adapter.yaml
odoo/addons/connector_algolia/tests/cassettes/TestAlgoliaBackend.test_index_adapter.yaml
odoo/addons/connector_algolia/tests/cassettes/TestAlgoliaBackend.test_index_adapter_clear.yaml
odoo/addons/connector_algolia/tests/cassettes/TestAlgoliaBackend.test_iter_adapter.yaml
odoo/addons/connector_algolia/views/se_backend_algolia.xml
odoo/addons/connector_algolia/views/se_menu.xml
odoo10_addon_connector_algolia-10.0.2.0.0.99.dev9.dist-info/METADATA
odoo10_addon_connector_algolia-10.0.2.0.0.99.dev9.dist-info/WHEEL
odoo10_addon_connector_algolia-10.0.2.0.0.99.dev9.dist-info/namespace_packages.txt
odoo10_addon_connector_algolia-10.0.2.0.0.99.dev9.dist-info/top_level.txt
odoo10_addon_connector_algolia-10.0.2.0.0.99.dev9.dist-info/RECORD
